phovea_processing_similarity/__init__.py
phovea_processing_similarity/api.py
phovea_processing_similarity/config.json
phovea_processing_similarity/similarity.py
phovea_processing_similarity/tasks.py
phovea_processing_similarity-5.0.0.dist-info/LICENSE
phovea_processing_similarity-5.0.0.dist-info/METADATA
phovea_processing_similarity-5.0.0.dist-info/WHEEL
phovea_processing_similarity-5.0.0.dist-info/entry_points.txt
phovea_processing_similarity-5.0.0.dist-info/top_level.txt
phovea_processing_similarity-5.0.0.dist-info/RECORD
