Metadata-Version: 2.1
Name: phovea-processing-similarity
Version: 5.0.0
Summary: Processing queue plugin to compute similarities for categorical data of matrices, tables, and stratifications
Home-page: https://phovea.caleydo.org
Author: The Caleydo Team
Author-email: contact@caleydo.org
License: BSD-3-Clause
Platform: UNKNOWN
Classifier: Intended Audience :: Developers
Classifier: Operating System :: OS Independent
Classifier: License :: OSI Approved :: BSD License
Classifier: Programming Language :: Python
Classifier: Programming Language :: Python :: 3.7
Requires-Dist: phovea-processing-queue (<7.0.0,>=6.0.0)
Requires-Dist: phovea-server (<8.0.0,>=7.0.0)
